optimum_benchmark/__init__.py
optimum_benchmark/cli.py
optimum_benchmark/hub_utils.py
optimum_benchmark/import_utils.py
optimum_benchmark/logging_utils.py
optimum_benchmark/process_utils.py
optimum_benchmark/system_utils.py
optimum_benchmark/task_utils.py
optimum_benchmark/version.py
optimum_benchmark/backends/__init__.py
optimum_benchmark/backends/base.py
optimum_benchmark/backends/config.py
optimum_benchmark/backends/diffusers_utils.py
optimum_benchmark/backends/peft_utils.py
optimum_benchmark/backends/timm_utils.py
optimum_benchmark/backends/transformers_utils.py
optimum_benchmark/backends/ipex/__init__.py
optimum_benchmark/backends/ipex/backend.py
optimum_benchmark/backends/ipex/config.py
optimum_benchmark/backends/ipex/utils.py
optimum_benchmark/backends/llama_cpp/__init__.py
optimum_benchmark/backends/llama_cpp/backend.py
optimum_benchmark/backends/llama_cpp/config.py
optimum_benchmark/backends/onnxruntime/__init__.py
optimum_benchmark/backends/onnxruntime/backend.py
optimum_benchmark/backends/onnxruntime/config.py
optimum_benchmark/backends/onnxruntime/utils.py
optimum_benchmark/backends/openvino/__init__.py
optimum_benchmark/backends/openvino/backend.py
optimum_benchmark/backends/openvino/config.py
optimum_benchmark/backends/openvino/utils.py
optimum_benchmark/backends/py_txi/__init__.py
optimum_benchmark/backends/py_txi/backend.py
optimum_benchmark/backends/py_txi/config.py
optimum_benchmark/backends/pytorch/__init__.py
optimum_benchmark/backends/pytorch/backend.py
optimum_benchmark/backends/pytorch/config.py
optimum_benchmark/backends/tensorrt_llm/__init__.py
optimum_benchmark/backends/tensorrt_llm/backend.py
optimum_benchmark/backends/tensorrt_llm/config.py
optimum_benchmark/backends/tensorrt_llm/utils.py
optimum_benchmark/backends/vllm/__init__.py
optimum_benchmark/backends/vllm/backend.py
optimum_benchmark/backends/vllm/config.py
optimum_benchmark/benchmark/__init__.py
optimum_benchmark/benchmark/base.py
optimum_benchmark/benchmark/config.py
optimum_benchmark-0.6.0.dist-info/METADATA
optimum_benchmark-0.6.0.dist-info/WHEEL
optimum_benchmark-0.6.0.dist-info/entry_points.txt
optimum_benchmark-0.6.0.dist-info/licenses/LICENSE
optimum_benchmark-0.6.0.dist-info/RECORD
