Metadata-Version: 2.4
Name: optimum-benchmark
Version: 0.6.0
Summary: Optimum-Benchmark is a unified multi-backend utility for benchmarking Transformers, Timm, Diffusers and Sentence-Transformers with full support of Optimum's hardware optimizations & quantization schemes.
Project-URL: Homepage, https://github.com/huggingface/optimum-benchmark
Project-URL: Repository, https://github.com/huggingface/optimum-benchmark
Project-URL: Issues, https://github.com/huggingface/optimum-benchmark/issues
Author: HuggingFace Inc. Special Ops Team
License-Expression: Apache-2.0
License-File: LICENSE
Keywords: benchmark,bitsandbytes,codecarbon,deepspeed,diffusers,flash-attn,gptqmodel,graphcore,habana,hpu,inference,intel,ipex,ipu,llama-cpp,llm-swarm,neural compressor,onnx,onnx runtime,optimization,peft,pruning,py-txi,quantization,sentence-transformers,timm,training,transformers,vllm
Classifier: Intended Audience :: Developers
Classifier: Intended Audience :: Education
Classifier: Intended Audience :: Science/Research
Classifier: License :: OSI Approved :: Apache Software License
Classifier: Operating System :: POSIX :: Linux
Classifier: Programming Language :: Python :: 3.10
Classifier: Programming Language :: Python :: 3.11
Classifier: Programming Language :: Python :: 3.12
Classifier: Programming Language :: Python :: 3.13
Classifier: Topic :: Scientific/Engineering :: Artificial Intelligence
Requires-Python: >=3.10
Requires-Dist: accelerate
Requires-Dist: colorlog
Requires-Dist: datasets>=4.0.0
Requires-Dist: flatten-dict
Requires-Dist: hf-xet
Requires-Dist: huggingface-hub
Requires-Dist: hydra-core
Requires-Dist: nvidia-ml-py
Requires-Dist: omegaconf
Requires-Dist: pandas
Requires-Dist: psutil
Requires-Dist: rich
Requires-Dist: transformers
Requires-Dist: typing-extensions
Provides-Extra: bitsandbytes
Requires-Dist: bitsandbytes; extra == 'bitsandbytes'
Provides-Extra: codecarbon
Requires-Dist: codecarbon; extra == 'codecarbon'
Provides-Extra: deepspeed
Requires-Dist: deepspeed<0.16.0; extra == 'deepspeed'
Provides-Extra: dev
Requires-Dist: codecarbon; extra == 'dev'
Requires-Dist: hydra-joblib-launcher; extra == 'dev'
Requires-Dist: mock; extra == 'dev'
Requires-Dist: pytest; extra == 'dev'
Requires-Dist: ruff; extra == 'dev'
Requires-Dist: torchcodec; (sys_platform != 'win32') and extra == 'dev'
Provides-Extra: diffusers
Requires-Dist: diffusers; extra == 'diffusers'
Provides-Extra: flash-attn
Requires-Dist: flash-attn; extra == 'flash-attn'
Provides-Extra: gptqmodel
Requires-Dist: gptqmodel; extra == 'gptqmodel'
Requires-Dist: optimum; extra == 'gptqmodel'
Provides-Extra: ipex
Requires-Dist: intel-extension-for-pytorch==2.8; extra == 'ipex'
Requires-Dist: optimum[ipex]>=1.27.0; extra == 'ipex'
Requires-Dist: torch==2.8; extra == 'ipex'
Provides-Extra: llama-cpp
Requires-Dist: llama-cpp-python; extra == 'llama-cpp'
Provides-Extra: onnxruntime
Requires-Dist: optimum[onnxruntime]>=1.27.0; extra == 'onnxruntime'
Provides-Extra: onnxruntime-gpu
Requires-Dist: optimum[onnxruntime-gpu]>=1.27.0; extra == 'onnxruntime-gpu'
Provides-Extra: openvino
Requires-Dist: optimum[openvino]>=1.27.0; extra == 'openvino'
Provides-Extra: peft
Requires-Dist: peft; extra == 'peft'
Provides-Extra: py-txi
Requires-Dist: py-txi; extra == 'py-txi'
Provides-Extra: sentence-transformers
Requires-Dist: sentence-transformers; extra == 'sentence-transformers'
Provides-Extra: tensorrt-llm
Requires-Dist: huggingface-hub<0.26.0; extra == 'tensorrt-llm'
Provides-Extra: timm
Requires-Dist: timm; extra == 'timm'
Provides-Extra: torchao
Requires-Dist: torchao; extra == 'torchao'
Provides-Extra: vllm
Requires-Dist: vllm; extra == 'vllm'
